amqpcli-0.0.1.data/scripts/amqpcli
amqpcli-0.0.1.dist-info/METADATA
amqpcli-0.0.1.dist-info/RECORD
amqpcli-0.0.1.dist-info/WHEEL
amqpcli-0.0.1.dist-info/top_level.txt
lib/__init__.py
lib/app.py
lib/argument.py
lib/banner.py
lib/error.py
lib/user_interface.py
lib/version.py
lib/handlers/__init__.py
lib/handlers/base_handler.py
lib/handlers/exchange_handlers.py
lib/handlers/message_handlers.py
lib/handlers/queue_handlers.py
