Metadata-Version: 2.1
Name: amqpcli
Version: 0.0.1
Summary: a Python interactive shell to act as an AMQP client
Home-page: https://github.com/Martin91/amqpcli
Author: Martin Hong
Author-email: hongzeqin@gmail.com
License: UNKNOWN
Platform: UNKNOWN
Classifier: Programming Language :: Python :: 2.7
Classifier: Programming Language :: Python :: 3
Classifier: Topic :: Communications
Classifier: License :: OSI Approved :: MIT License
Classifier: Operating System :: OS Independent
